optimem/__init__.py
optimem/main.py
pytorch_optimem-0.0.5.dist-info/LICENSE
pytorch_optimem-0.0.5.dist-info/METADATA
pytorch_optimem-0.0.5.dist-info/WHEEL
pytorch_optimem-0.0.5.dist-info/top_level.txt
pytorch_optimem-0.0.5.dist-info/RECORD
